Metadata-Version: 2.4
Name: gerbls
Version: 0.8.0
Author-email: Kristo Ment <kristo.ment@gmail.com>
License-Expression: MIT
Project-URL: Documentation, https://gerbls.readthedocs.io/
Project-URL: Repository, https://github.com/kment/GERBLS.git
Classifier: Programming Language :: Python :: 3 :: Only
Classifier: Programming Language :: Python :: 3.9
Classifier: Programming Language :: Python :: 3.10
Classifier: Programming Language :: Python :: 3.11
Classifier: Programming Language :: Python :: 3.12
Classifier: Programming Language :: C
Classifier: Topic :: Scientific/Engineering :: Astronomy
Requires-Python: >=3.9
License-File: LICENSE
Requires-Dist: numpy>=1.20
Requires-Dist: scipy
Provides-Extra: extras
Requires-Dist: batman-package; extra == "extras"
Requires-Dist: matplotlib; extra == "extras"
Requires-Dist: pytest; extra == "extras"
Dynamic: license-file
